code_wallet/__init__.py
code_wallet/client/__init__.py
code_wallet/client/connection.py
code_wallet/client/errors.py
code_wallet/client/intents.py
code_wallet/library/__init__.py
code_wallet/library/currency.py
code_wallet/library/errors.py
code_wallet/library/idempotency.py
code_wallet/library/keypair.py
code_wallet/library/kin.py
code_wallet/library/message.py
code_wallet/library/payload.py
code_wallet/library/payment_request.py
code_wallet/library/publickey.py
code_wallet/library/rendezvous.py
code_wallet/library/utils.py
tests/__init__.py
tests/test_client.py
tests/test_currency.py
tests/test_idempotency.py
tests/test_keypair.py
tests/test_kin.py
tests/test_message.py
tests/test_payload.py
tests/test_payment_request.py
tests/test_publickey.py
code_wallet-1.0.7.dist-info/LICENCE.md
code_wallet-1.0.7.dist-info/METADATA
code_wallet-1.0.7.dist-info/WHEEL
code_wallet-1.0.7.dist-info/top_level.txt
code_wallet-1.0.7.dist-info/RECORD
