Metadata-Version: 2.1
Name: code-wallet
Version: 1.0.7
Summary: UNKNOWN
Home-page: https://github.com/code-wallet/code-sdk-python
License: UNKNOWN
Platform: UNKNOWN
License-File: LICENCE.md
Requires-Dist: pynacl
Requires-Dist: base58
Requires-Dist: requests
